setup.py
falcon_api/__init__.py
falcon_api/app.py
falcon_api/request.py
falcon_api/response.py
falcon_api.egg-info/PKG-INFO
falcon_api.egg-info/SOURCES.txt
falcon_api.egg-info/dependency_links.txt
falcon_api.egg-info/requires.txt
falcon_api.egg-info/top_level.txt
falcon_api/__pycache__/__init__.cpython-34.pyc
falcon_api/__pycache__/app.cpython-34.pyc
falcon_api/__pycache__/request.cpython-34.pyc
falcon_api/__pycache__/response.cpython-34.pyc